README.md
setup.cfg
setup.py
FaucetML.egg-info/PKG-INFO
FaucetML.egg-info/SOURCES.txt
FaucetML.egg-info/dependency_links.txt
FaucetML.egg-info/requires.txt
FaucetML.egg-info/top_level.txt
faucetml/__init__.py
faucetml/data_reader.py
faucetml/utils.py
faucetml.egg-info/PKG-INFO
faucetml.egg-info/SOURCES.txt
faucetml.egg-info/dependency_links.txt
faucetml.egg-info/requires.txt
faucetml.egg-info/top_level.txt
faucetml/preprocessing/__init__.py
faucetml/preprocessing/identify_types.py
faucetml/preprocessing/norm_metadata.py
faucetml/preprocessing/normalization.py
faucetml/preprocessing/preprocessor_net.py
faucetml/preprocessing/sparse_to_dense.py