Metadata-Version: 2.1
Name: faucetml
Version: 0.0.2
Summary: Simple, high-speed batch data reader for ML applications.
Home-page: https://github.com/econti/FaucetML
Author: Edoardo Conti, Lionel Vital
Author-email: edoardo.conti@gmail.com
License: UNKNOWN
Download-URL: https://github.com/econti/FaucetML/archive/v0.0.1.tar.gz
Platform: UNKNOWN
Classifier: Programming Language :: Python :: 3
Classifier: License :: OSI Approved :: MIT License
Classifier: Operating System :: OS Independent
Requires-Python: >=3.6
